FedJust/__init__.py
FedJust/aggregators/aggregator.py
FedJust/aggregators/fedopt_aggregator.py
FedJust/files/archive.py
FedJust/files/handlers.py
FedJust/files/loggers.py
FedJust/model/federated_model.py
FedJust/node/federated_node.py
FedJust/operations/evaluations.py
FedJust/operations/orchestrations.py
FedJust/simulation/adaptive_optimizer_simulation.py
FedJust/simulation/simulation.py
FedJust/utils/computations.py
fedjust-0.1.2.5.dist-info/METADATA
fedjust-0.1.2.5.dist-info/WHEEL
fedjust-0.1.2.5.dist-info/RECORD
