Metadata-Version: 2.1
Name: FedJust
Version: 0.1.2.5
Summary: 
Author: Scolpe
Author-email: 63779111+Scolpe@users.noreply.github.com
Requires-Python: >=3.10,<4.0
Classifier: Programming Language :: Python :: 3
Classifier: Programming Language :: Python :: 3.10
Classifier: Programming Language :: Python :: 3.11
Classifier: Programming Language :: Python :: 3.12
Requires-Dist: datasets (>=2.17.0)
Requires-Dist: numpy (>=1.2.6)
Requires-Dist: scikit-learn (>=1.4)
Requires-Dist: torch (>=2.2.0)
Requires-Dist: torchvision (>=0.1.5)
